brainaccess/__init__.py
brainaccess/libload.py
brainaccess/py.typed
brainaccess/connect/__init__.py
brainaccess/connect/processor.py
brainaccess/core/__init__.py
brainaccess/core/annotation.py
brainaccess/core/battery_info.py
brainaccess/core/ble_device.py
brainaccess/core/charging_settings.py
brainaccess/core/device_features.py
brainaccess/core/device_info.py
brainaccess/core/device_model.py
brainaccess/core/eeg_channel.py
brainaccess/core/eeg_manager.py
brainaccess/core/full_battery_info.py
brainaccess/core/gain_mode.py
brainaccess/core/impedance_measurement_mode.py
brainaccess/core/log_level.py
brainaccess/core/polarity.py
brainaccess/core/sBacore_config_t.py
brainaccess/core/stream_rate.py
brainaccess/core/version.py
brainaccess/examples/example_eeg_acquisition_to_mne.py
brainaccess/examples/example_eeg_processing.py
brainaccess/examples/example_impedance_measurement.py
brainaccess/examples/example_minimal_eeg_acquisition.py
brainaccess/lib/libbabciconnect.so
brainaccess/lib/libbabciconnect.so.2.4.0
brainaccess/lib/libbacore.so
brainaccess/lib/libbacore.so.3.6.0
brainaccess/lib/libsimpleble.so
brainaccess/lib/libsimpleble.so.0
brainaccess/lib/libsimpleble.so.0.6.2
brainaccess/utils/__init__.py
brainaccess/utils/acquisition.py
brainaccess/utils/exceptions.py
brainaccess.libs/libatlas-5b5475a4.so.3.10.3
brainaccess.libs/libcblas-8a8944d5.so.3.10.3
brainaccess.libs/libdbus-1-c5c41a4c.so.3.19.11
brainaccess.libs/libgcrypt-f648d4ed.so.20.2.5
brainaccess.libs/libgfortran-01fc7210.so.5.0.0
brainaccess.libs/libgpg-error-df95914e.so.0.28.0
brainaccess.libs/liblapack-72d177d2.so.3
brainaccess.libs/liblz4-d6574e34.so.1.9.2
brainaccess.libs/liblzma-79a1dbc7.so.5.2.4
brainaccess.libs/libquadmath-36ccd8fd.so.0.0.0
brainaccess.libs/libsystemd-4d12bf8d.so.0.28.0
brainaccess-3.6.0.dist-info/METADATA
brainaccess-3.6.0.dist-info/WHEEL
brainaccess-3.6.0.dist-info/RECORD
brainaccess-3.6.0.dist-info/licenses/LICENSE.md
