Metadata-Version: 2.4
Name: brainaccess
Version: 3.6.0
Summary: BrainAccess Python API
Project-URL: homepage, https://www.brainaccess.ai/
Project-URL: documentation, https://www.brainaccess.ai/software/brainaccess-sdk/
Author-email: neurotechnology <brainaccess@neurotechnology.com>
License-File: LICENSE.md
Keywords: BCI,EEG,brainaccess,neuroscience
Classifier: Intended Audience :: Developers
Classifier: Intended Audience :: Healthcare Industry
Classifier: Intended Audience :: Science/Research
Classifier: License :: Other/Proprietary License
Classifier: Natural Language :: English
Classifier: Operating System :: Microsoft :: Windows
Classifier: Operating System :: OS Independent
Classifier: Operating System :: POSIX :: Linux
Classifier: Programming Language :: Python :: 3
Classifier: Programming Language :: Python :: 3.8
Classifier: Programming Language :: Python :: 3.9
Classifier: Programming Language :: Python :: 3.10
Classifier: Programming Language :: Python :: 3.11
Classifier: Programming Language :: Python :: 3.12
Classifier: Programming Language :: Python :: 3.13
Classifier: Topic :: Scientific/Engineering
Classifier: Topic :: Software Development
Classifier: Topic :: Software Development :: Libraries
Requires-Python: >=3.8
Requires-Dist: matplotlib
Requires-Dist: mne
Requires-Dist: multimethod
Requires-Dist: numpy
Requires-Dist: pandas
Requires-Dist: pyyaml
